cfrate/__init__.py
cfrate/browserhandles.py
cfrate/command.py
cfrate/filehandles.py
cfrate/ts.py
cfrate-3.0.4.dist-info/METADATA
cfrate-3.0.4.dist-info/WHEEL
cfrate-3.0.4.dist-info/entry_points.txt
cfrate-3.0.4.dist-info/licence
cfrate-3.0.4.dist-info/top_level.txt
cfrate-3.0.4.dist-info/RECORD
