Metadata-Version: 2.1
Name: cfrate
Version: 3.0.4
Summary: play a file sound - song- once the rating changes at all the participants  of some round. Also if a handle was given the program will output the the changes to that handle
Home-page: https://github.com/theunderdog/Codeforces-rateDetector
Author: theunderdog
Author-email: ahmedbonumstelio@gmail.com
License: UNKNOWN
Platform: UNKNOWN
Classifier: Programming Language :: Python :: 3
Classifier: License :: OSI Approved :: MIT License
Classifier: Operating System :: OS Independent
